princeffinfo/__init__.py
princeffinfo/account_info.py
princeffinfo-0.1.2.dist-info/METADATA
princeffinfo-0.1.2.dist-info/WHEEL
princeffinfo-0.1.2.dist-info/top_level.txt
princeffinfo-0.1.2.dist-info/RECORD
